{"ENDS:m":["άλμπουμ"],"(n)":["άνθος","πένθος","θνητός","κερνώ","διώχνω","φτιάχνω","ζώνη","αρνί","κοινός","πυκνός","συχνός","αχνός","λαχνός","καπνός","κύκνος","λιγνός","ίχνος","γοργόνα","κάρβουνο","κυβερνώ","δελφίνι","πυρήνας","αγκώνας","αιώνας","γεγονός","χριστιανός","ίντερνετ","σουβενίρ","υπεύθυνος","γωνία","ανδρεία","κονσέρβα","εννοώ","αγνοώ","κυνήγι","λυχνάρι","φρόνηση","ρύπανση","έναρξη","άγνωστος","τεχνίτης","συνθέτης","συνοικία","αναίδεια","ανέχεια","τυραννία","συνδυάζω","πανηγύρι","ανύπαρκτος","ένα","κάνω","είναι","έκανε","έννοια","γέννησε","κινήθηκε","μπορούσανε"],"(m)":["γράμμα","βόμβα","άμμος","ράμφος","κομψός","αμμουδιά","σύμπτωμα","συμμαχία","πλημμυρίζω","αμφιβάλλω","αμφισβητώ","αίμα","κλίμα","βλέμμα","δέρμα","γεύμα","βρομιά","σύρμα","φράγμα","φόρμα","δραχμή","κορμί","στιγμή","δήμος","λαιμός","γκρεμός","θερμός","ατμός","βαθμός","σταθμός","κόμικς","άρωμα","δόλωμα","πρόβλημα","πρόγραμμα","κάθισμα","ίδρυμα","έθιμο","έντομο","ηγούμαι","βιάζομαι","βαριέμαι","έρχομαι","ασήμι","αφορμή","χρήσιμος","άσχημος","εύθυμος","αριθμός","ρατσισμός","ελάττωμα","διάλειμμα","κατόρθωμα","παράδειγμα","επιθυμώ","επιστήμη","επιδρομή","διάσημος","ηλεκτρισμός","άμιλλα","ημέρα","καμήλα","αμελώ","θυμίζω","φάρμακο","αρμέγω","αμοιβή","αμέσως","βρόμικος","τολμηρός","τεκμήριο","επιμελής","είμαι","άμα","κάμω","έκαμε","γέμισε","παίζαμε","κοιμήθηκε"],"BEGINS:m (n m)":["μήνυμα","μνημείο","μνήμη","μέριμνα"],"ENDS:n":["ζαμπόν","κολλάν","καλσόν","κραγιόν","κλόουν","επείγον","δωρεάν","παρελθόν","μπέικον"],"BEGINS:m ENDS:n":["μέλλον"],"(n) ENDS:n":["φωνήεν"],"BEGINS:m":["μάντρα","μακρύς","μασκότ","μέτωπο","μάθηση","μου","μισή","μισεί","μισοί"],"(n m)":["λίμνη","γυμνός","θάμνος","αίνιγμα","αρνούμαι","άνεμος","συνάλλαγμα","αισθάνομαι","επιμονή","αναδρομή","άμυνα","ζυμώνω","στριμώχνω","θέρμανση","αρμονία","αδημονώ","πνεύμα","σεμνός","σμήνος","ύμνος","συναίσθημα","στάμνα","σκαμνί","αμνός","καμίνι","γυμναστής","καμινάδα","κομοδίνο","σεμνότητα","αμνηστία","γυμνάσιο","γυμναστική","γνώμη"],"(n m*)":["αριθμημένη"],"BEGINS:n":["νεύρο","νησί","νεκρός","νωρίς","ναύτης","νου"],"(m) ENDS:n":["εμβαδόν","γουόκμαν","πούλμαν"],"(n*)":["τονώνω","κινδυνεύω"],"(m*)":["τμήμα"],"BEGINS:m (n* m)":["μνημονεύω"],"BEGINS:m (m)":["μυρμήγκι"],"BEGINS:m (n)":["μορφώνω","μόλυνση","μαγνήτης","μένω","μήνας","μήνυση"],"(n* m)":["φαινόμενο","πνεύμονας","ισχυρογνώμονας"],"(n* m*)":["απομνημόνευση","αξιομνημόνευτο"],"(ɲ)":["άπνοια","ξαφνιάζω","γκρινιάρης","σαφήνεια","αδράνεια"]}
